README.md
setup.py
tests/test_vol_mom.py
vol_mom_pkg/__init__.py
vol_mom_pkg/broker_info.py
vol_mom_pkg/data.py
vol_mom_pkg/signals.py
vol_mom_pkg/trade.py
vol_mom_pkg.egg-info/PKG-INFO
vol_mom_pkg.egg-info/SOURCES.txt
vol_mom_pkg.egg-info/dependency_links.txt
vol_mom_pkg.egg-info/requires.txt
vol_mom_pkg.egg-info/top_level.txt