Metadata-Version: 2.2
Name: vol_mom_pkg
Version: 0.1.9
Summary: Volatility and momentum strategy, trades executed with Alpaca
Author: Cassel Robson
Author-email: robs7000@mylaurier.ca
Classifier: Programming Language :: Python :: 3.8
Requires-Dist: pandas
Requires-Dist: pandas_datareader
Requires-Dist: alpaca-trade-api
Requires-Dist: numpy
Requires-Dist: yfinance
Requires-Dist: python-dotenv
Requires-Dist: setuptools
Dynamic: author
Dynamic: author-email
Dynamic: classifier
Dynamic: requires-dist
Dynamic: summary
